{
    "event_id": 213,
    "Date": "2022-07-08",
    "main_attraction": "Metallica",
    "Event": "NOS Alive",
    "Venue": "Passeio Mar\u00edtimo de Alg\u00e9s",
    "Location": "Lisbon,Portugal",
    "Latitude": "38.7077507",
    "Longitude": "-9.1365919",
    "Is_cancelled": "No",
    "Tour": "nan",
    "Other_acts": "nan",
    "Concert_details": "nan",
    "Concert_profile_link": "https://www.metallica.com/tour/2022-07-08-lisbon-portugal.html",
    "Songs": "Whiplash, Creeping Death, Enter Sandman, Cyanide, Wherever I May Roam, Nothing Else Matters, Dirty Window, Sad But True, Whiskey in the Jar, For Whom the Bell Tolls, Moth Into Flame, Fade to Black, Seek & Destroy, Damage, Inc., One, Master of Puppets"
}